{
  "version": 1,
  "config": {
    "bundle": {
      "git": {
        "branch": "main",
        "origin_url": "https://github.com/gzuz101/dab-tests",
        "commit": "4bececaed31037ae7506344e406d46d56d1a23f7",
        "bundle_root_path": "."
      }
    },
    "workspace": {
      "file_path": "/Workspace/Repos/gaurav.m.sahu@v4c.ai/dab-tests/files"
    },
    "resources": {
      "jobs": {
        "unified_orders_dlt_daily_job": {
          "id": "813683037026862",
          "relative_path": "databricks.yml"
        }
      },
      "pipelines": {
        "unified_orders_dlt": {
          "id": "20e46474-3ed9-4a5a-b8d7-13a0ca6cc0dc",
          "relative_path": "databricks.yml"
        }
      }
    },
    "presets": {
      "source_linked_deployment": false
    }
  },
  "extra": {}
}